splunk_sdk/__init__.py
splunk_sdk/__version__.py
splunk_sdk/base_client.py
splunk_sdk/base_service.py
splunk_sdk/splunk_cloud.py
splunk_sdk/action/__init__.py
splunk_sdk/action/v1beta2/__init__.py
splunk_sdk/action/v1beta2/gen_action_service_api.py
splunk_sdk/action/v1beta2/gen_models.py
splunk_sdk/action/v2alpha1/__init__.py
splunk_sdk/action/v2alpha1/gen_action_service_api.py
splunk_sdk/action/v2alpha1/gen_models.py
splunk_sdk/app_registry/__init__.py
splunk_sdk/app_registry/v1beta2/__init__.py
splunk_sdk/app_registry/v1beta2/gen_app_registry_api.py
splunk_sdk/app_registry/v1beta2/gen_models.py
splunk_sdk/auth/__init__.py
splunk_sdk/auth/auth_manager.py
splunk_sdk/catalog/__init__.py
splunk_sdk/catalog/v2alpha2/__init__.py
splunk_sdk/catalog/v2alpha2/gen_metadata_catalog_api.py
splunk_sdk/catalog/v2alpha2/gen_models.py
splunk_sdk/catalog/v2beta1/__init__.py
splunk_sdk/catalog/v2beta1/gen_metadata_catalog_api.py
splunk_sdk/catalog/v2beta1/gen_models.py
splunk_sdk/collect/__init__.py
splunk_sdk/collect/v1beta1/__init__.py
splunk_sdk/collect/v1beta1/gen_collect_service_api.py
splunk_sdk/collect/v1beta1/gen_models.py
splunk_sdk/common/__init__.py
splunk_sdk/common/context.py
splunk_sdk/common/sscmodel.py
splunk_sdk/forwarders/__init__.py
splunk_sdk/forwarders/v2beta1/__init__.py
splunk_sdk/forwarders/v2beta1/gen_models.py
splunk_sdk/forwarders/v2beta1/gen_splunk_forwarder_service_api.py
splunk_sdk/gateway/__init__.py
splunk_sdk/gateway/client.py
splunk_sdk/gateway/results.py
splunk_sdk/identity/__init__.py
splunk_sdk/identity/v2beta1/__init__.py
splunk_sdk/identity/v2beta1/gen_identity_api.py
splunk_sdk/identity/v2beta1/gen_models.py
splunk_sdk/identity/v3/__init__.py
splunk_sdk/identity/v3/gen_identity_api.py
splunk_sdk/identity/v3/gen_models.py
splunk_sdk/identity/v3alpha1/__init__.py
splunk_sdk/identity/v3alpha1/gen_identity_api.py
splunk_sdk/identity/v3alpha1/gen_models.py
splunk_sdk/ingest/__init__.py
splunk_sdk/ingest/ingest_event_batcher.py
splunk_cloud_sdk-12.0.0.dist-info/LICENSE.txt
splunk_cloud_sdk-12.0.0.dist-info/METADATA
splunk_cloud_sdk-12.0.0.dist-info/WHEEL
splunk_cloud_sdk-12.0.0.dist-info/top_level.txt
splunk_cloud_sdk-12.0.0.dist-info/RECORD
