Metadata-Version: 2.1
Name: splunk-cloud-sdk
Version: 12.0.0
Summary: SDK for the Splunk Developer Cloud platform
Home-page: UNKNOWN
Author: Splunk
Author-email: dev@splunk.com
License: MIT
Platform: UNKNOWN
Classifier: Development Status :: 3 - Alpha
Requires-Dist: requests (<2.23,>=2.22.0)
Requires-Dist: urllib3 (<1.26,>=1.25.2)
Provides-Extra: dev
Requires-Dist: pep8 (<2,>=1.7.1) ; extra == 'dev'
Requires-Dist: sphinx (<3,>=2.0.1) ; extra == 'dev'
Requires-Dist: sphinxcontrib-apidoc (>=0.3.0) ; extra == 'dev'
Requires-Dist: cryptography (<2.7,>=2.6.1) ; extra == 'dev'
Provides-Extra: test
Requires-Dist: coverage (<5,>=4.5.3) ; extra == 'test'
Requires-Dist: flake8 (<4,>=3.7.7) ; extra == 'test'
Requires-Dist: pytest (<5,>=4.4.0) ; extra == 'test'
